[{"season":2011,"gender":"Men","event_no":"800 meter","wa_event":"800m","orientation":"lower","top_n":200,"athletes_total":388,"results_total":388,"points_available":388,"avg_points_top_n":745.45,"avg_value_top_n_perf":120.89025,"avg_perf_top_n":"2,00,89","event_order":3},{"season":2012,"gender":"Men","event_no":"800 meter","wa_event":"800m","orientation":"lower","top_n":200,"athletes_total":434,"results_total":434,"points_available":434,"avg_points_top_n":750.125,"avg_value_top_n_perf":120.65415,"avg_perf_top_n":"2,00,65","event_order":3},{"season":2013,"gender":"Men","event_no":"800 meter","wa_event":"800m","orientation":"lower","top_n":200,"athletes_total":468,"results_total":468,"points_available":468,"avg_points_top_n":776.85,"avg_value_top_n_perf":119.54215,"avg_perf_top_n":"1,59,54","event_order":3},{"season":2014,"gender":"Men","event_no":"800 meter","wa_event":"800m","orientation":"lower","top_n":200,"athletes_total":450,"results_total":450,"points_available":450,"avg_points_top_n":765.92,"avg_value_top_n_perf":119.9943,"avg_perf_top_n":"1,59,99","event_order":3},{"season":2015,"gender":"Men","event_no":"800 meter","wa_event":"800m","orientation":"lower","top_n":200,"athletes_total":480,"results_total":480,"points_available":480,"avg_points_top_n":758.615,"avg_value_top_n_perf":120.28225,"avg_perf_top_n":"2,00,28","event_order":3},{"season":2016,"gender":"Men","event_no":"800 meter","wa_event":"800m","orientation":"lower","top_n":200,"athletes_total":502,"results_total":502,"points_available":502,"avg_points_top_n":763.62,"avg_value_top_n_perf":120.08075,"avg_perf_top_n":"2,00,08","event_order":3},{"season":2017,"gender":"Men","event_no":"800 meter","wa_event":"800m","orientation":"lower","top_n":200,"athletes_total":450,"results_total":450,"points_available":450,"avg_points_top_n":750.72,"avg_value_top_n_perf":120.6344,"avg_perf_top_n":"2,00,63","event_order":3},{"season":2018,"gender":"Men","event_no":"800 meter","wa_event":"800m","orientation":"lower","top_n":200,"athletes_total":504,"results_total":504,"points_available":504,"avg_points_top_n":737.105,"avg_value_top_n_perf":121.2162,"avg_perf_top_n":"2,01,22","event_order":3},{"season":2019,"gender":"Men","event_no":"800 meter","wa_event":"800m","orientation":"lower","top_n":200,"athletes_total":475,"results_total":475,"points_available":475,"avg_points_top_n":734.77,"avg_value_top_n_perf":121.35185,"avg_perf_top_n":"2,01,35","event_order":3},{"season":2020,"gender":"Men","event_no":"800 meter","wa_event":"800m","orientation":"lower","top_n":200,"athletes_total":306,"results_total":306,"points_available":306,"avg_points_top_n":712.795,"avg_value_top_n_perf":122.3628,"avg_perf_top_n":"2,02,36","event_order":3},{"season":2021,"gender":"Men","event_no":"800 meter","wa_event":"800m","orientation":"lower","top_n":200,"athletes_total":379,"results_total":379,"points_available":379,"avg_points_top_n":740.305,"avg_value_top_n_perf":121.1014,"avg_perf_top_n":"2,01,10","event_order":3},{"season":2022,"gender":"Men","event_no":"800 meter","wa_event":"800m","orientation":"lower","top_n":200,"athletes_total":345,"results_total":345,"points_available":345,"avg_points_top_n":725.71,"avg_value_top_n_perf":121.75735,"avg_perf_top_n":"2,01,76","event_order":3},{"season":2023,"gender":"Men","event_no":"800 meter","wa_event":"800m","orientation":"lower","top_n":200,"athletes_total":376,"results_total":376,"points_available":376,"avg_points_top_n":741.58,"avg_value_top_n_perf":121.04875,"avg_perf_top_n":"2,01,05","event_order":3},{"season":2024,"gender":"Men","event_no":"800 meter","wa_event":"800m","orientation":"lower","top_n":200,"athletes_total":393,"results_total":393,"points_available":393,"avg_points_top_n":765.28,"avg_value_top_n_perf":120.0337,"avg_perf_top_n":"2,00,03","event_order":3},{"season":2025,"gender":"Men","event_no":"800 meter","wa_event":"800m","orientation":"lower","top_n":200,"athletes_total":357,"results_total":357,"points_available":357,"avg_points_top_n":748.24,"avg_value_top_n_perf":120.81205,"avg_perf_top_n":"2,00,81","event_order":3}]