[{"season":2011,"gender":"Men","event_no":"5000 meter","wa_event":"5000m","orientation":"lower","top_n":100,"athletes_total":111,"results_total":111,"points_available":111,"avg_points_top_n":604.44,"avg_value_top_n_perf":982.0329,"avg_perf_top_n":"16,22,03","event_order":6},{"season":2012,"gender":"Men","event_no":"5000 meter","wa_event":"5000m","orientation":"lower","top_n":100,"athletes_total":158,"results_total":158,"points_available":158,"avg_points_top_n":652.9,"avg_value_top_n_perf":958.5586,"avg_perf_top_n":"15,58,56","event_order":6},{"season":2013,"gender":"Men","event_no":"5000 meter","wa_event":"5000m","orientation":"lower","top_n":100,"athletes_total":206,"results_total":206,"points_available":206,"avg_points_top_n":706.83,"avg_value_top_n_perf":937.7864,"avg_perf_top_n":"15,37,79","event_order":6},{"season":2014,"gender":"Men","event_no":"5000 meter","wa_event":"5000m","orientation":"lower","top_n":100,"athletes_total":232,"results_total":232,"points_available":232,"avg_points_top_n":739.83,"avg_value_top_n_perf":925.3831,"avg_perf_top_n":"15,25,38","event_order":6},{"season":2015,"gender":"Men","event_no":"5000 meter","wa_event":"5000m","orientation":"lower","top_n":100,"athletes_total":235,"results_total":235,"points_available":235,"avg_points_top_n":763.02,"avg_value_top_n_perf":917.4558,"avg_perf_top_n":"15,17,46","event_order":6},{"season":2016,"gender":"Men","event_no":"5000 meter","wa_event":"5000m","orientation":"lower","top_n":100,"athletes_total":210,"results_total":210,"points_available":210,"avg_points_top_n":728.58,"avg_value_top_n_perf":930.1692,"avg_perf_top_n":"15,30,17","event_order":6},{"season":2017,"gender":"Men","event_no":"5000 meter","wa_event":"5000m","orientation":"lower","top_n":100,"athletes_total":229,"results_total":229,"points_available":229,"avg_points_top_n":750.34,"avg_value_top_n_perf":922.3483,"avg_perf_top_n":"15,22,35","event_order":6},{"season":2018,"gender":"Men","event_no":"5000 meter","wa_event":"5000m","orientation":"lower","top_n":100,"athletes_total":236,"results_total":236,"points_available":236,"avg_points_top_n":730.97,"avg_value_top_n_perf":930.2766,"avg_perf_top_n":"15,30,28","event_order":6},{"season":2019,"gender":"Men","event_no":"5000 meter","wa_event":"5000m","orientation":"lower","top_n":100,"athletes_total":282,"results_total":282,"points_available":282,"avg_points_top_n":792.94,"avg_value_top_n_perf":907.559,"avg_perf_top_n":"15,07,56","event_order":6},{"season":2020,"gender":"Men","event_no":"5000 meter","wa_event":"5000m","orientation":"lower","top_n":100,"athletes_total":410,"results_total":410,"points_available":410,"avg_points_top_n":856.04,"avg_value_top_n_perf":885.8161,"avg_perf_top_n":"14,45,82","event_order":6},{"season":2021,"gender":"Men","event_no":"5000 meter","wa_event":"5000m","orientation":"lower","top_n":100,"athletes_total":407,"results_total":407,"points_available":407,"avg_points_top_n":872.0,"avg_value_top_n_perf":880.7372,"avg_perf_top_n":"14,40,74","event_order":6},{"season":2022,"gender":"Men","event_no":"5000 meter","wa_event":"5000m","orientation":"lower","top_n":100,"athletes_total":325,"results_total":325,"points_available":325,"avg_points_top_n":843.09,"avg_value_top_n_perf":890.4134,"avg_perf_top_n":"14,50,41","event_order":6},{"season":2023,"gender":"Men","event_no":"5000 meter","wa_event":"5000m","orientation":"lower","top_n":100,"athletes_total":309,"results_total":309,"points_available":309,"avg_points_top_n":843.78,"avg_value_top_n_perf":890.3964,"avg_perf_top_n":"14,50,40","event_order":6},{"season":2024,"gender":"Men","event_no":"5000 meter","wa_event":"5000m","orientation":"lower","top_n":100,"athletes_total":365,"results_total":365,"points_available":365,"avg_points_top_n":849.97,"avg_value_top_n_perf":888.1103,"avg_perf_top_n":"14,48,11","event_order":6},{"season":2025,"gender":"Men","event_no":"5000 meter","wa_event":"5000m","orientation":"lower","top_n":100,"athletes_total":274,"results_total":274,"points_available":274,"avg_points_top_n":850.33,"avg_value_top_n_perf":888.389,"avg_perf_top_n":"14,48,39","event_order":6}]