[{"season":2002,"gender":"Women","event_no":"100 meter","wa_event":"100m","orientation":"lower","top_n":100,"athletes_total":104,"results_total":104,"points_available":104,"avg_points_top_n":837.88,"avg_value_top_n_perf":12.8139,"avg_perf_top_n":"12,81","event_order":0},{"season":2002,"gender":"Women","event_no":"1500 meter","wa_event":"1500m","orientation":"lower","top_n":100,"athletes_total":89,"results_total":89,"points_available":89,"avg_points_top_n":798.483,"avg_value_top_n_perf":296.658876,"avg_perf_top_n":"4,56,66","event_order":4},{"season":2002,"gender":"Women","event_no":"200 meter","wa_event":"200m","orientation":"lower","top_n":100,"athletes_total":108,"results_total":108,"points_available":108,"avg_points_top_n":820.61,"avg_value_top_n_perf":26.3838,"avg_perf_top_n":"26,38","event_order":1},{"season":2002,"gender":"Women","event_no":"400 meter","wa_event":"400m","orientation":"lower","top_n":100,"athletes_total":99,"results_total":99,"points_available":99,"avg_points_top_n":813.818,"avg_value_top_n_perf":60.788485,"avg_perf_top_n":"1,00,79","event_order":2},{"season":2002,"gender":"Women","event_no":"800 meter","wa_event":"800m","orientation":"lower","top_n":100,"athletes_total":102,"results_total":102,"points_available":102,"avg_points_top_n":803.37,"avg_value_top_n_perf":142.1224,"avg_perf_top_n":"2,22,12","event_order":3},{"season":2002,"gender":"Women","event_no":"Høyde","wa_event":"HJ","orientation":"higher","top_n":100,"athletes_total":79,"results_total":79,"points_available":79,"avg_points_top_n":806.025,"avg_value_top_n_perf":1.574557,"avg_perf_top_n":"1,57","event_order":15},{"season":2002,"gender":"Women","event_no":"Tresteg","wa_event":"TJ","orientation":"higher","top_n":100,"athletes_total":78,"results_total":78,"points_available":78,"avg_points_top_n":813.026,"avg_value_top_n_perf":10.987692,"avg_perf_top_n":"10,99","event_order":18}]